django_lexpy/__init__.py
django_lexpy/apps.py
django_lexpy/commands/__init__.py
django_lexpy/commands/lexpy.py
django_lexpy/commands/sample_files/init_sample
django_lexpy/commands/sample_files/messages_sample
django_lexpy/templatetags/__init__.py
django_lexpy/templatetags/lexpy.py
django_lexpy/tests.py
django_lexpy-0.1.1.dist-info/LICENSE
django_lexpy-0.1.1.dist-info/METADATA
django_lexpy-0.1.1.dist-info/WHEEL
django_lexpy-0.1.1.dist-info/entry_points.txt
django_lexpy-0.1.1.dist-info/RECORD
